setup.cfg
setup.py
amqp_middleware.egg-info/PKG-INFO
amqp_middleware.egg-info/SOURCES.txt
amqp_middleware.egg-info/dependency_links.txt
amqp_middleware.egg-info/entry_points.txt
amqp_middleware.egg-info/requires.txt
amqp_middleware.egg-info/top_level.txt
amqpconsumer/__init__.py
amqpconsumer/components/__init__.py
amqpconsumer/components/agent.py
amqpconsumer/components/connection.py
amqpconsumer/components/manager.py
tests/__init__.py
tests/test.py