Metadata-Version: 1.0
Name: amqp-middleware
Version: 1.1.2
Summary: AMQP Consumer-Publisher Middleware
Home-page: https://github.com/mistio/amqp-middleware
Author: Chris Pollalis
Author-email: cpollalis@mist.io
License: Apache
Platform: UNKNOWN
